valis/__init__.py
valis/affine_optimizer.py
valis/data/bf_formats.txt
valis/feature_detectors.py
valis/feature_matcher.py
valis/micro_rigid_registrar.py
valis/non_rigid_registrars.py
valis/preprocessing.py
valis/registration.py
valis/serial_non_rigid.py
valis/serial_rigid.py
valis/slide_io.py
valis/slide_tools.py
valis/superglue_models/__init__.py
valis/superglue_models/matching.py
valis/superglue_models/superglue.py
valis/superglue_models/superpoint.py
valis/superglue_models/utils.py
valis/superglue_models/weights/superglue_indoor.pth
valis/superglue_models/weights/superglue_outdoor.pth
valis/superglue_models/weights/superpoint_v1.pth
valis/valtils.py
valis/viz.py
valis/warp_tools.py
valis_wsi-1.2.0.dist-info/METADATA
valis_wsi-1.2.0.dist-info/WHEEL
valis_wsi-1.2.0.dist-info/entry_points.txt
valis_wsi-1.2.0.dist-info/licenses/LICENSE.txt
valis_wsi-1.2.0.dist-info/RECORD
